odoo/addons/hr_employee_birthday_mail/README.rst
odoo/addons/hr_employee_birthday_mail/__init__.py
odoo/addons/hr_employee_birthday_mail/__manifest__.py
odoo/addons/hr_employee_birthday_mail/data/data.xml
odoo/addons/hr_employee_birthday_mail/data/ir_cron.xml
odoo/addons/hr_employee_birthday_mail/i18n/es.po
odoo/addons/hr_employee_birthday_mail/i18n/fr.po
odoo/addons/hr_employee_birthday_mail/i18n/fr_FR.po
odoo/addons/hr_employee_birthday_mail/i18n/hr_employee_birthday_mail.pot
odoo/addons/hr_employee_birthday_mail/i18n/it.po
odoo/addons/hr_employee_birthday_mail/models/__init__.py
odoo/addons/hr_employee_birthday_mail/models/hr_employee.py
odoo/addons/hr_employee_birthday_mail/models/res_user.py
odoo/addons/hr_employee_birthday_mail/readme/CONFIGURE.md
odoo/addons/hr_employee_birthday_mail/readme/CONTRIBUTORS.md
odoo/addons/hr_employee_birthday_mail/readme/DESCRIPTION.md
odoo/addons/hr_employee_birthday_mail/readme/USAGE.md
odoo/addons/hr_employee_birthday_mail/static/description/icon.png
odoo/addons/hr_employee_birthday_mail/static/description/index.html
odoo/addons/hr_employee_birthday_mail/views/hr_employee_views.xml
odoo/addons/hr_employee_birthday_mail/views/res_user_views.xml
odoo_addon_hr_employee_birthday_mail-18.0.1.0.0.2.dist-info/METADATA
odoo_addon_hr_employee_birthday_mail-18.0.1.0.0.2.dist-info/WHEEL
odoo_addon_hr_employee_birthday_mail-18.0.1.0.0.2.dist-info/top_level.txt
odoo_addon_hr_employee_birthday_mail-18.0.1.0.0.2.dist-info/RECORD
